saturn5/__init__.py
saturn5/saturn5.py
saturn5-0.0.1.dist-info/LICENSE
saturn5-0.0.1.dist-info/METADATA
saturn5-0.0.1.dist-info/WHEEL
saturn5-0.0.1.dist-info/top_level.txt
saturn5-0.0.1.dist-info/RECORD
