Metadata-Version: 2.1
Name: saturn5
Version: 0.0.1
Summary: A example Python package
Home-page: 
Author: Felipe Sá
Author-email: f.sa.felipe.sa@gmail.com
License: Apache License 2.0
Platform: UNKNOWN
Classifier: Development Status :: 1 - Planning
Classifier: Intended Audience :: Developers
Classifier: License :: OSI Approved :: Apache Software License
Classifier: Programming Language :: Python :: 3
